gitlab_pr_analyzer/__init__.py
gitlab_pr_analyzer/ai_analyzer.py
gitlab_pr_analyzer/cli.py
gitlab_pr_analyzer/commit_collector.py
gitlab_pr_analyzer/config.py
gitlab_pr_analyzer/diff_provider.py
gitlab_pr_analyzer/gitlab_client.py
gitlab_pr_analyzer/matcher.py
gitlab_pr_analyzer/mr_collector.py
gitlab_pr_analyzer/mr_exporter.py
gitlab_pr_analyzer/smart_search_analyzer.py
gitlab_pr_analyzer/utils.py
gitlab_pr_analyzer-0.9.3.dist-info/METADATA
gitlab_pr_analyzer-0.9.3.dist-info/WHEEL
gitlab_pr_analyzer-0.9.3.dist-info/entry_points.txt
gitlab_pr_analyzer-0.9.3.dist-info/top_level.txt
gitlab_pr_analyzer-0.9.3.dist-info/RECORD
