Metadata-Version: 2.4
Name: gitlab-pr-analyzer
Version: 0.9.3
Summary: Intelligent tool for collecting, analyzing, and summarizing GitLab Merge Requests and commits
Home-page: https://example.com/gitlab-pr-analyzer
Author: GitLab PR Analyzer Team
Requires-Python: >=3.8
Requires-Dist: click>=8.1.0
Requires-Dist: rich>=13.0.0
Requires-Dist: requests>=2.31.0
Requires-Dist: python-gitlab>=3.15.0
Requires-Dist: python-dateutil>=2.8.2
Requires-Dist: fuzzywuzzy>=0.18.0
Requires-Dist: python-levenshtein>=0.21.0
Dynamic: author
Dynamic: description
Dynamic: description-content-type
Dynamic: home-page
Dynamic: requires-dist
Dynamic: requires-python
Dynamic: summary
